[
    {
        "name": "libraries",
        "buildType": "publishOnly",
        "repos": [
            {
                "repo": "library_cli",
                "repo_url": "https://github.com/thzero/library_cli.git",
                "scope": "@thzero",
                "wait": true
            },
            {
                "repo": "library_common",
                "repo_url": "https://github.com/thzero/library_common.git",
                "scope": "@thzero",
                "wait": true
            },
            {
                "repo": "library_common_service",
                "repo_url": "https://github.com/thzero/library_common_service.git",
                "scope": "@thzero",
                "wait": true
            },
            {
                "name": "library_client...",
                "repos": [
                    {
                        "repo": "library_client",
                        "repo_url": "https://github.com/thzero/library_client.git",
                        "scope": "@thzero",
                        "wait": true
                    },
                    {
                        "name": "library_client services...",
                        "repos": [
                            {
                                "repo": "library_client_firebase",
                                "repo_url": "https://github.com/thzero/library_client_firebase.git",
                                "scope": "@thzero",
                                "wait": false
                            },
                            {
                                "repo": "library_client_service_rest_axios",
                                "repo_url": "https://github.com/thzero/library_client_service_rest_axios.git",
                                "scope": "@thzero",
                                "wait": false
                            },
                            {
                                "repo": "library_client_service_rest_fetch",
                                "repo_url": "https://github.com/thzero/library_client_service_rest_fetch.git",
                                "scope": "@thzero",
                                "wait": false
                            }
                        ],
                        "wait": false
                    },
                    {
                        "repo": "library_client_vue",
                        "repo_url": "https://github.com/thzero/library_client_vue.git",
                        "scope": "@thzero",
                        "wait": true
                    },
                    {
                        "repo": "library_client_vue3",
                        "repo_url": "https://github.com/thzero/library_client_vue3.git",
                        "scope": "@thzero",
                        "wait": true
                    }
                ],
                "wait": false
            }
        ]
    }
]